baiduspider/__init__.py
baiduspider/_spider.py
baiduspider/parser.py
baiduspider/errors/__init__.py
tests/__init__.py
tests/test_pic.py
tests/test_web.py
BaiduSpider-0.0.3.dist-info/LICENSE
BaiduSpider-0.0.3.dist-info/METADATA
BaiduSpider-0.0.3.dist-info/WHEEL
BaiduSpider-0.0.3.dist-info/top_level.txt
BaiduSpider-0.0.3.dist-info/RECORD
