Metadata-Version: 2.1
Name: BaiduSpider
Version: 0.0.3
Summary: BaiduSpider，一个爬取百度的利器
Home-page: https://github.com/BaiduSpider/BaiduSpider
Author: Sam Zhang
Author-email: samzhang951@outlook.com
License: UNKNOWN
Platform: UNKNOWN
Classifier: Programming Language :: Python :: 3
Classifier: License :: OSI Approved :: MIT License
Classifier: Development Status :: 3 - Alpha
Requires-Python: >=3.6
Requires-Dist: requests
Requires-Dist: bs4
Requires-Dist: htmlmin
